{"title":"bel air park 9002505-201","main category":"Dining Room","sub category":"","img":"https://www.amini.com/images/collections/9002000/9002505-201.jpg","description":"\n                            <ul class=\"list-unstyled lighting-description\">\n                               <li> No: <span itemprop=\"brand\">9002505-201</span>  <font color=\"red\"> * </font> \n                               </li>\n                                  \n                                    <li><span class=\"title3\">Dimensions:</span> \n                                        <div id=\"dimensions\"> </div>\n                                    </li>  \n                                \n                               \n                                 <!--Start Top cavity-->\n                                                                  \n                                 <!--End Top cavity-->\n                                  \n                                    <li><span class=\"title3\">Finish:</span>\n                                      Champagne</li>\n                                  \n                            </ul>\n                                <p class=\"lighting-description\" style=\"text-align:left;\"><font color=\"red\"> * </font> <i>Indicates items that are currently in stock in our domestic warehouse.</i> </p>\n                                  \n                        "}
{"title":"silverlake village KI-SLVG007-129","main category":"Dining Room","sub category":"","img":"https://www.amini.com/images/collections/SLVRLKVLAG/KI-SLVG007-129.jpg","description":"\n                            <ul class=\"list-unstyled lighting-description\">\n                               <li> No: <span itemprop=\"brand\">KI-SLVG007-129</span>  <font color=\"red\"> * </font> \n                               </li>\n                                  \n                                    <li><span class=\"title3\">Dimensions:</span> \n                                        <div id=\"dimensions\"> </div>\n                                    </li>  \n                                \n                               \n                                 <!--Start Top cavity-->\n                                                                  \n                                 <!--End Top cavity-->\n                                  \n                                    <li><span class=\"title3\">Finish:</span>\n                                      Washed Oak</li>\n                                  \n                            </ul>\n                                <p class=\"lighting-description\" style=\"text-align:left;\"><font color=\"red\"> * </font> <i>Indicates items that are currently in stock in our domestic warehouse.</i> </p>\n                                  \n                        "}
{"title":"hollywood swank NT03505-11","main category":"Dining Room","sub category":"","img":"https://www.amini.com/images/collections/03000NT/NT03505-11.jpg","description":"\n                            <ul class=\"list-unstyled lighting-description\">\n                               <li> No: <span itemprop=\"brand\">NT03505-11</span>  <font color=\"red\"> * </font> \n                               </li>\n                                  \n                                    <li><span class=\"title3\">Dimensions:</span> \n                                        <div id=\"dimensions\"> </div>\n                                    </li>  \n                                \n                               \n                                 <!--Start Top cavity-->\n                                                                  \n                                 <!--End Top cavity-->\n                                  \n                                    <li><span class=\"title3\">Finish:</span>\n                                      Pearl Caviar</li>\n                                  \n                            </ul>\n                               \n                                        <img src=\"images/finish/Finish_11.jpg\" title=\"FINISH\" alt=\" \" style=\"margin-left:10px\">\n                                     <p class=\"lighting-description\" style=\"text-align:left;\"><font color=\"red\"> * </font> <i>Indicates items that are currently in stock in our domestic warehouse.</i> </p>\n                                  \n                        "}
{"title":"bella veneto 9051067-202","main category":"Dining Room","sub category":"","img":"https://www.amini.com/images/collections/9051000/9051067-202.jpg","description":"\n                            <ul class=\"list-unstyled lighting-description\">\n                               <li> No: <span itemprop=\"brand\">9051067-202</span>  <font color=\"red\"> * </font> \n                               </li>\n                                  \n                                    <li><span class=\"title3\">Dimensions:</span> \n                                        <div id=\"dimensions\"> </div>\n                                    </li>  \n                                \n                               \n                                 <!--Start Top cavity-->\n                                                                  \n                                 <!--End Top cavity-->\n                                  \n                                    <li><span class=\"title3\">Finish:</span>\n                                      Cognac</li>\n                                  \n                            </ul>\n                               \n                                        <img src=\"images/finish/Finish_202.jpg\" title=\"FINISH\" alt=\" \" style=\"margin-left:10px\">\n                                     <p class=\"lighting-description\" style=\"text-align:left;\"><font color=\"red\"> * </font> <i>Indicates items that are currently in stock in our domestic warehouse.</i> </p>\n                                  \n                        "}
{"title":"halo 9018003A-116","main category":"Dining Room","sub category":"","img":"https://www.amini.com/images/collections/9018000/9018003A-116.jpg","description":"\n                            <ul class=\"list-unstyled lighting-description\">\n                               <li> No: <span itemprop=\"brand\">9018003A-116</span>  <font color=\"red\"> * </font> \n                               </li>\n                                  \n                                    <li><span class=\"title3\">Dimensions:</span> \n                                        <div id=\"dimensions\"> </div>\n                                    </li>  \n                                \n                               \n                                 <!--Start Top cavity-->\n                                                                  \n                                 <!--End Top cavity-->\n                                  \n                                    <li><span class=\"title3\">Finish:</span>\n                                      Glossy White</li>\n                                  \n                            </ul>\n                                <p class=\"lighting-description\" style=\"text-align:left;\"><font color=\"red\"> * </font> <i>Indicates items that are currently in stock in our domestic warehouse.</i> </p>\n                                  \n                        "}
{"title":"bel air park 9002260-201","main category":"Dining Room","sub category":"","img":"https://www.amini.com/images/collections/9002000/9002260-201.jpg","description":"\n                            <ul class=\"list-unstyled lighting-description\">\n                               <li> No: <span itemprop=\"brand\">9002260-201</span>  <font color=\"red\"> * </font> \n                               </li>\n                                  \n                                    <li><span class=\"title3\">Dimensions:</span> \n                                        <div id=\"dimensions\"> </div>\n                                    </li>  \n                                \n                               \n                                 <!--Start Top cavity-->\n                                                                  \n                                 <!--End Top cavity-->\n                                  \n                                    <li><span class=\"title3\">Finish:</span>\n                                      Champagne</li>\n                                  \n                            </ul>\n                                <p class=\"lighting-description\" style=\"text-align:left;\"><font color=\"red\"> * </font> <i>Indicates items that are currently in stock in our domestic warehouse.</i> </p>\n                                  \n                        "}
{"title":"grand masterpiece 9050067-402","main category":"Dining Room","sub category":"","img":"https://www.amini.com/images/collections/9050000/9050067-402.jpg","description":"\n                            <ul class=\"list-unstyled lighting-description\">\n                               <li> No: <span itemprop=\"brand\">9050067-402</span>  <font color=\"red\"> * </font> \n                               </li>\n                                  \n                                    <li><span class=\"title3\">Dimensions:</span> \n                                        <div id=\"dimensions\"> </div>\n                                    </li>  \n                                \n                               \n                                 <!--Start Top cavity-->\n                                                                  \n                                 <!--End Top cavity-->\n                                  \n                                    <li><span class=\"title3\">Finish:</span>\n                                      Royal Sienna</li>\n                                  \n                            </ul>\n                                <p class=\"lighting-description\" style=\"text-align:left;\"><font color=\"red\"> * </font> <i>Indicates items that are currently in stock in our domestic warehouse.</i> </p>\n                                  \n                        "}
{"title":"overture 08004RN-10","main category":"Dining Room","sub category":"","img":"https://www.amini.com/images/collections/08000/08004RN-10.jpg","description":"\n                            <ul class=\"list-unstyled lighting-description\">\n                               <li> No: <span itemprop=\"brand\">08004RN-10</span>  <font color=\"red\"> * </font> \n                               </li>\n                                  \n                                    <li><span class=\"title3\">Dimensions:</span> \n                                        <div id=\"dimensions\"> </div>\n                                    </li>  \n                                \n                               \n                                 <!--Start Top cavity-->\n                                                                  \n                                 <!--End Top cavity-->\n                                  \n                                    <li><span class=\"title3\">Finish:</span>\n                                      Champagne</li>\n                                  \n                            </ul>\n                               \n                                        <img src=\"images/finish/Finish_10.jpg\" title=\"FINISH\" alt=\" \" style=\"margin-left:10px\">\n                                     <p class=\"lighting-description\" style=\"text-align:left;\"><font color=\"red\"> * </font> <i>Indicates items that are currently in stock in our domestic warehouse.</i> </p>\n                                  \n                        "}
{"title":"hollywood loft 9001604-08","main category":"Dining Room","sub category":"","img":"https://www.amini.com/images/collections/9001000/9001604-08.jpg","description":"\n                            <ul class=\"list-unstyled lighting-description\">\n                               <li> No: <span itemprop=\"brand\">9001604-08</span>  <font color=\"red\"> * </font> \n                               </li>\n                                  \n                                    <li><span class=\"title3\">Dimensions:</span> \n                                        <div id=\"dimensions\"> </div>\n                                    </li>  \n                                \n                               \n                                 <!--Start Top cavity-->\n                                                                  \n                                 <!--End Top cavity-->\n                                  \n                                    <li><span class=\"title3\">Finish:</span>\n                                      Pearl</li>\n                                  \n                            </ul>\n                               \n                                        <img src=\"images/finish/Finish_08.jpg\" title=\"FINISH\" alt=\" \" style=\"margin-left:10px\">\n                                     <p class=\"lighting-description\" style=\"text-align:left;\"><font color=\"red\"> * </font> <i>Indicates items that are currently in stock in our domestic warehouse.</i> </p>\n                                  \n                        "}
{"title":"bel air park 9002505-405-201","main category":"Dining Room","sub category":"","img":"https://www.amini.com/images/collections/9002000/9002505-405-201.jpg","description":"\n                            <ul class=\"list-unstyled lighting-description\">\n                               <li> No: <span itemprop=\"brand\">9002505-405-201</span>  <font color=\"red\"> * </font> \n                               </li>\n                                  \n                                    <li><span class=\"title3\">Dimensions:</span> \n                                        <div id=\"dimensions\"> </div>\n                                    </li>  \n                                \n                               \n                                 <!--Start Top cavity-->\n                                                                  \n                                 <!--End Top cavity-->\n                                  \n                                    <li><span class=\"title3\">Finish:</span>\n                                      Champagne</li>\n                                  \n                            </ul>\n                                <p class=\"lighting-description\" style=\"text-align:left;\"><font color=\"red\"> * </font> <i>Indicates items that are currently in stock in our domestic warehouse.</i> </p>\n                                  \n                        "}
{"title":"21 cosmopolitan taupe 9029505S-212","main category":"Dining Room","sub category":"","img":"https://www.amini.com/images/collections/9029000T/9029505S-212.jpg","description":"\n                            <ul class=\"list-unstyled lighting-description\">\n                               <li> No: <span itemprop=\"brand\">9029505S-212</span>  <font color=\"red\"> * </font> \n                               </li>\n                                  \n                                    <li><span class=\"title3\">Dimensions:</span> \n                                        <div id=\"dimensions\"> </div>\n                                    </li>  \n                                \n                               \n                                 <!--Start Top cavity-->\n                                                                  \n                                 <!--End Top cavity-->\n                                  \n                                    <li><span class=\"title3\">Finish:</span>\n                                       Pebble Grain Taupe/Umber</li>\n                                  \n                            </ul>\n                                <p class=\"lighting-description\" style=\"text-align:left;\"><font color=\"red\"> * </font> <i>Indicates items that are currently in stock in our domestic warehouse.</i> </p>\n                                  \n                        "}
{"title":"overture 08003RN-10","main category":"Dining Room","sub category":"","img":"https://www.amini.com/images/collections/08000/08003RN-10.jpg","description":"\n                            <ul class=\"list-unstyled lighting-description\">\n                               <li> No: <span itemprop=\"brand\">08003RN-10</span>  <font color=\"red\"> * </font> \n                               </li>\n                                  \n                                    <li><span class=\"title3\">Dimensions:</span> \n                                        <div id=\"dimensions\"> </div>\n                                    </li>  \n                                \n                               \n                                 <!--Start Top cavity-->\n                                                                  \n                                 <!--End Top cavity-->\n                                  \n                                    <li><span class=\"title3\">Finish:</span>\n                                      Champagne</li>\n                                  \n                            </ul>\n                               \n                                        <img src=\"images/finish/Finish_10.jpg\" title=\"FINISH\" alt=\" \" style=\"margin-left:10px\">\n                                     <p class=\"lighting-description\" style=\"text-align:left;\"><font color=\"red\"> * </font> <i>Indicates items that are currently in stock in our domestic warehouse.</i> </p>\n                                  \n                        "}
{"title":"hollywood loft 9001603-08","main category":"Dining Room","sub category":"","img":"https://www.amini.com/images/collections/9001000/9001603-08.jpg","description":"\n                            <ul class=\"list-unstyled lighting-description\">\n                               <li> No: <span itemprop=\"brand\">9001603-08</span>  <font color=\"red\"> * </font> \n                               </li>\n                                  \n                                    <li><span class=\"title3\">Dimensions:</span> \n                                        <div id=\"dimensions\"> </div>\n                                    </li>  \n                                \n                               \n                                 <!--Start Top cavity-->\n                                                                  \n                                 <!--End Top cavity-->\n                                  \n                                    <li><span class=\"title3\">Finish:</span>\n                                      Pearl</li>\n                                  \n                            </ul>\n                               \n                                        <img src=\"images/finish/Finish_08.jpg\" title=\"FINISH\" alt=\" \" style=\"margin-left:10px\">\n                                     <p class=\"lighting-description\" style=\"text-align:left;\"><font color=\"red\"> * </font> <i>Indicates items that are currently in stock in our domestic warehouse.</i> </p>\n                                  \n                        "}
{"title":"laguna ridge 9083004-814","main category":"Dining Room","sub category":"","img":"https://www.amini.com/images/collections/9083000/9083004-814.jpg","description":"\n                            <ul class=\"list-unstyled lighting-description\">\n                               <li> No: <span itemprop=\"brand\">9083004-814</span>  <font color=\"red\"> * </font> \n                               </li>\n                                  \n                                    <li><span class=\"title3\">Dimensions:</span> \n                                        <div id=\"dimensions\"> </div>\n                                    </li>  \n                                \n                               \n                                 <!--Start Top cavity-->\n                                                                  \n                                 <!--End Top cavity-->\n                                  \n                                    <li><span class=\"title3\">Finish:</span>\n                                      Brushed Silver</li>\n                                  \n                            </ul>\n                                <p class=\"lighting-description\" style=\"text-align:left;\"><font color=\"red\"> * </font> <i>Indicates items that are currently in stock in our domestic warehouse.</i> </p>\n                                  \n                        "}
{"title":"carrollton collection KI-CRLN003-407N","main category":"Dining Room","sub category":"","img":"https://www.amini.com/images/collections/CARLLTON-N/KI-CRLN003-407N.jpg","description":"\n                            <ul class=\"list-unstyled lighting-description\">\n                               <li> No: <span itemprop=\"brand\">KI-CRLN003-407N</span>  <font color=\"red\"> * </font> \n                               </li>\n                                  \n                                    <li><span class=\"title3\">Dimensions:</span> \n                                        <div id=\"dimensions\"> </div>\n                                    </li>  \n                                \n                               \n                                 <!--Start Top cavity-->\n                                                                  \n                                 <!--End Top cavity-->\n                                  \n                                    <li><span class=\"title3\">Finish:</span>\n                                      Rustic Ranch</li>\n                                  \n                            </ul>\n                                <p class=\"lighting-description\" style=\"text-align:left;\"><font color=\"red\"> * </font> <i>Indicates items that are currently in stock in our domestic warehouse.</i> </p>\n                                  \n                        "}
{"title":"valise 9026600-110","main category":"Dining Room","sub category":"","img":"https://www.amini.com/images/collections/9026000/9026600-110.jpg","description":"\n                            <ul class=\"list-unstyled lighting-description\">\n                               <li> No: <span itemprop=\"brand\">9026600-110</span>  <font color=\"red\"> * </font> \n                               </li>\n                                  \n                                    <li><span class=\"title3\">Dimensions:</span> \n                                        <div id=\"dimensions\"> </div>\n                                    </li>  \n                                \n                               \n                                 <!--Start Top cavity-->\n                                                                  \n                                 <!--End Top cavity-->\n                                  \n                                    <li><span class=\"title3\">Finish:</span>\n                                      Amazon Tan Gator</li>\n                                  \n                            </ul>\n                               \n                                        <img src=\"images/finish/Finish_110.jpg\" title=\"FINISH\" alt=\" \" style=\"margin-left:10px\">\n                                     <p class=\"lighting-description\" style=\"text-align:left;\"><font color=\"red\"> * </font> <i>Indicates items that are currently in stock in our domestic warehouse.</i> </p>\n                                  \n                        "}
{"title":"tuscano melange 34067-34","main category":"Dining Room","sub category":"","img":"https://www.amini.com/images/collections/34000M/34067-34.jpg","description":"\n                            <ul class=\"list-unstyled lighting-description\">\n                               <li> No: <span itemprop=\"brand\">34067-34</span>  <font color=\"red\"> * </font> \n                               </li>\n                                  \n                                    <li><span class=\"title3\">Dimensions:</span> \n                                        <div id=\"dimensions\"> </div>\n                                    </li>  \n                                \n                               \n                                 <!--Start Top cavity-->\n                                                                  \n                                 <!--End Top cavity-->\n                                  \n                                    <li><span class=\"title3\">Finish:</span>\n                                      Melange</li>\n                                  \n                            </ul>\n                               \n                                        <img src=\"images/finish/Finish_34.jpg\" title=\"FINISH\" alt=\" \" style=\"margin-left:10px\">\n                                     <p class=\"lighting-description\" style=\"text-align:left;\"><font color=\"red\"> * </font> <i>Indicates items that are currently in stock in our domestic warehouse.</i> </p>\n                                  \n                        "}
{"title":"hollywood loft 9001600-104","main category":"Dining Room","sub category":"","img":"https://www.amini.com/images/collections/9001000/9001600-104.jpg","description":"\n                            <ul class=\"list-unstyled lighting-description\">\n                               <li> No: <span itemprop=\"brand\">9001600-104</span>  <font color=\"red\"> * </font> \n                               </li>\n                                  \n                                    <li><span class=\"title3\">Dimensions:</span> \n                                        <div id=\"dimensions\"> </div>\n                                    </li>  \n                                \n                               \n                                 <!--Start Top cavity-->\n                                                                  \n                                 <!--End Top cavity-->\n                                  \n                                    <li><span class=\"title3\">Finish:</span>\n                                      Frost</li>\n                                  \n                            </ul>\n                               \n                                        <img src=\"images/finish/Finish_104.jpg\" title=\"FINISH\" alt=\" \" style=\"margin-left:10px\">\n                                     <p class=\"lighting-description\" style=\"text-align:left;\"><font color=\"red\"> * </font> <i>Indicates items that are currently in stock in our domestic warehouse.</i> </p>\n                                  \n                        "}
{"title":"silverlake village KI-SLVG003-129","main category":"Dining Room","sub category":"","img":"https://www.amini.com/images/collections/SLVRLKVLAG/KI-SLVG003-129.jpg","description":"\n                            <ul class=\"list-unstyled lighting-description\">\n                               <li> No: <span itemprop=\"brand\">KI-SLVG003-129</span>  <font color=\"red\"> * </font> \n                               </li>\n                                  \n                                    <li><span class=\"title3\">Dimensions:</span> \n                                        <div id=\"dimensions\"> </div>\n                                    </li>  \n                                \n                               \n                                 <!--Start Top cavity-->\n                                                                  \n                                 <!--End Top cavity-->\n                                  \n                                    <li><span class=\"title3\">Finish:</span>\n                                      Washed Oak</li>\n                                  \n                            </ul>\n                                <p class=\"lighting-description\" style=\"text-align:left;\"><font color=\"red\"> * </font> <i>Indicates items that are currently in stock in our domestic warehouse.</i> </p>\n                                  \n                        "}
{"title":"brooklyn walk KI-BRKW067-408","main category":"Dining Room","sub category":"","img":"https://www.amini.com/images/collections/BRKLYNWALK/KI-BRKW067-408.jpg","description":"\n                            <ul class=\"list-unstyled lighting-description\">\n                               <li> No: <span itemprop=\"brand\">KI-BRKW067-408</span>  <font color=\"red\"> * </font> \n                               </li>\n                                  \n                                    <li><span class=\"title3\">Dimensions:</span> \n                                        <div id=\"dimensions\"> </div>\n                                    </li>  \n                                \n                               \n                                 <!--Start Top cavity-->\n                                                                  \n                                 <!--End Top cavity-->\n                                  \n                                    <li><span class=\"title3\">Finish:</span>\n                                      Burnt Umber</li>\n                                  \n                            </ul>\n                                <p class=\"lighting-description\" style=\"text-align:left;\"><font color=\"red\"> * </font> <i>Indicates items that are currently in stock in our domestic warehouse.</i> </p>\n                                  \n                        "}
{"title":"menlo station KI-MENP003A-123","main category":"Dining Room","sub category":"","img":"https://www.amini.com/images/collections/MENLOSTION/KI-MENP003A-123.jpg","description":"\n                            <ul class=\"list-unstyled lighting-description\">\n                               <li> No: <span itemprop=\"brand\">KI-MENP003A-123</span>  <font color=\"red\"> * </font> \n                               </li>\n                                  \n                                    <li><span class=\"title3\">Dimensions:</span> \n                                        <div id=\"dimensions\"> </div>\n                                    </li>  \n                                \n                               \n                                 <!--Start Top cavity-->\n                                                                  \n                                 <!--End Top cavity-->\n                                  \n                                    <li><span class=\"title3\">Finish:</span>\n                                      Eucalyptus</li>\n                                  \n                            </ul>\n                                <p class=\"lighting-description\" style=\"text-align:left;\"><font color=\"red\"> * </font> <i>Indicates items that are currently in stock in our domestic warehouse.</i> </p>\n                                  \n                        "}
{"title":"camden court 9005033-126","main category":"Dining Room","sub category":"","img":"https://www.amini.com/images/collections/9005000/9005033-126.jpg","description":"\n                            <ul class=\"list-unstyled lighting-description\">\n                               <li> No: <span itemprop=\"brand\">9005033-126</span>  <font color=\"red\"> * </font> \n                               </li>\n                                  \n                                    <li><span class=\"title3\">Dimensions:</span> \n                                        <div id=\"dimensions\"> </div>\n                                    </li>  \n                                \n                               \n                                 <!--Start Top cavity-->\n                                                                  \n                                 <!--End Top cavity-->\n                                  \n                                    <li><span class=\"title3\">Finish:</span>\n                                      Pearl</li>\n                                  \n                            </ul>\n                                <p class=\"lighting-description\" style=\"text-align:left;\"><font color=\"red\"> * </font> <i>Indicates items that are currently in stock in our domestic warehouse.</i> </p>\n                                  \n                        "}
{"title":"horizons 9012603-108","main category":"Dining Room","sub category":"","img":"https://www.amini.com/images/collections/9012000/9012603-108.jpg","description":"\n                            <ul class=\"list-unstyled lighting-description\">\n                               <li> No: <span itemprop=\"brand\">9012603-108</span>  <font color=\"red\"> * </font> \n                               </li>\n                                  \n                                    <li><span class=\"title3\">Dimensions:</span> \n                                        <div id=\"dimensions\"> </div>\n                                    </li>  \n                                \n                               \n                                 <!--Start Top cavity-->\n                                                                  \n                                 <!--End Top cavity-->\n                                  \n                                    <li><span class=\"title3\">Finish:</span>\n                                      Cloud White</li>\n                                  \n                            </ul>\n                                <p class=\"lighting-description\" style=\"text-align:left;\"><font color=\"red\"> * </font> <i>Indicates items that are currently in stock in our domestic warehouse.</i> </p>\n                                  \n                        "}
{"title":"villa valencia 72005-06-55","main category":"Dining Room","sub category":"","img":"https://www.amini.com/images/collections/72000/72005-06-55.jpg","description":"\n                            <ul class=\"list-unstyled lighting-description\">\n                               <li> No: <span itemprop=\"brand\">72005-06-55</span>  <font color=\"red\"> * </font> \n                               </li>\n                                  \n                                    <li><span class=\"title3\">Dimensions:</span> \n                                        <div id=\"dimensions\"> </div>\n                                    </li>  \n                                \n                               \n                                 <!--Start Top cavity-->\n                                                                  \n                                 <!--End Top cavity-->\n                                  \n                                    <li><span class=\"title3\">Finish:</span>\n                                      Classic Chestnut</li>\n                                  \n                            </ul>\n                               \n                                        <img src=\"images/finish/Finish_55.jpg\" title=\"FINISH\" alt=\" \" style=\"margin-left:10px\">\n                                     <p class=\"lighting-description\" style=\"text-align:left;\"><font color=\"red\"> * </font> <i>Indicates items that are currently in stock in our domestic warehouse.</i> </p>\n                                  \n                        "}
{"title":"villa di como heritage 9053067-207","main category":"Dining Room","sub category":"","img":"https://www.amini.com/images/collections/9053000H/9053067-207.jpg","description":"\n                            <ul class=\"list-unstyled lighting-description\">\n                               <li> No: <span itemprop=\"brand\">9053067-207</span>  <font color=\"red\"> * </font> \n                               </li>\n                                  \n                                    <li><span class=\"title3\">Dimensions:</span> \n                                        <div id=\"dimensions\"> </div>\n                                    </li>  \n                                \n                               \n                                 <!--Start Top cavity-->\n                                                                  \n                                 <!--End Top cavity-->\n                                  \n                                    <li><span class=\"title3\">Finish:</span>\n                                      Heritage</li>\n                                  \n                            </ul>\n                                <p class=\"lighting-description\" style=\"text-align:left;\"><font color=\"red\"> * </font> <i>Indicates items that are currently in stock in our domestic warehouse.</i> </p>\n                                  \n                        "}
{"title":"hollywood swank NT03002-11","main category":"Dining Room","sub category":"","img":"https://www.amini.com/images/collections/03000NT/NT03002-11.jpg","description":"\n                            <ul class=\"list-unstyled lighting-description\">\n                               <li> No: <span itemprop=\"brand\">NT03002-11</span>  <font color=\"red\"> * </font> \n                               </li>\n                                  \n                                    <li><span class=\"title3\">Dimensions:</span> \n                                        <div id=\"dimensions\"> </div>\n                                    </li>  \n                                \n                               \n                                 <!--Start Top cavity-->\n                                                                  \n                                 <!--End Top cavity-->\n                                  \n                                    <li><span class=\"title3\">Finish:</span>\n                                      Pearl Caviar</li>\n                                  \n                            </ul>\n                               \n                                        <img src=\"images/finish/Finish_11.jpg\" title=\"FINISH\" alt=\" \" style=\"margin-left:10px\">\n                                     <p class=\"lighting-description\" style=\"text-align:left;\"><font color=\"red\"> * </font> <i>Indicates items that are currently in stock in our domestic warehouse.</i> </p>\n                                  \n                        "}
{"title":"eclipse KI-ECLP004-135","main category":"Dining Room","sub category":"","img":"https://www.amini.com/images/collections/ECLIPSE/KI-ECLP004-135.jpg","description":"\n                            <ul class=\"list-unstyled lighting-description\">\n                               <li> No: <span itemprop=\"brand\">KI-ECLP004-135</span>  <font color=\"red\"> * </font> \n                               </li>\n                                  \n                                    <li><span class=\"title3\">Dimensions:</span> \n                                        <div id=\"dimensions\"> </div>\n                                    </li>  \n                                \n                               \n                                 <!--Start Top cavity-->\n                                                                  \n                                 <!--End Top cavity-->\n                                  \n                                    <li><span class=\"title3\">Finish:</span>\n                                      Moonlight</li>\n                                  \n                            </ul>\n                                <p class=\"lighting-description\" style=\"text-align:left;\"><font color=\"red\"> * </font> <i>Indicates items that are currently in stock in our domestic warehouse.</i> </p>\n                                  \n                        "}
{"title":"windsor court 70007-54","main category":"Dining Room","sub category":"","img":"https://www.amini.com/images/collections/70000/70007-54.jpg","description":"\n                            <ul class=\"list-unstyled lighting-description\">\n                               <li> No: <span itemprop=\"brand\">70007-54</span>  <font color=\"red\"> * </font> \n                               </li>\n                                  \n                                    <li><span class=\"title3\">Dimensions:</span> \n                                        <div id=\"dimensions\"> </div>\n                                    </li>  \n                                \n                               \n                                 <!--Start Top cavity-->\n                                                                  \n                                 <!--End Top cavity-->\n                                  \n                                    <li><span class=\"title3\">Finish:</span>\n                                      Vintage Fruitwood</li>\n                                  \n                            </ul>\n                               \n                                        <img src=\"images/finish/Finish_54.jpg\" title=\"FINISH\" alt=\" \" style=\"margin-left:10px\">\n                                     <p class=\"lighting-description\" style=\"text-align:left;\"><font color=\"red\"> * </font> <i>Indicates items that are currently in stock in our domestic warehouse.</i> </p>\n                                  \n                        "}
{"title":"lavelle 54005-6-04","main category":"Dining Room","sub category":"","img":"https://www.amini.com/images/collections/54000/54005-6-04.jpg","description":"\n                            <ul class=\"list-unstyled lighting-description\">\n                               <li> No: <span itemprop=\"brand\">54005-6-04</span>  <font color=\"red\"> * </font> \n                               </li>\n                                  \n                                    <li><span class=\"title3\">Dimensions:</span> \n                                        <div id=\"dimensions\"> </div>\n                                    </li>  \n                                \n                               \n                                 <!--Start Top cavity-->\n                                                                  \n                                 <!--End Top cavity-->\n                                  \n                                    <li><span class=\"title3\">Finish:</span>\n                                      Blanc</li>\n                                  \n                            </ul>\n                               \n                                        <img src=\"images/finish/Finish_04.jpg\" title=\"FINISH\" alt=\" \" style=\"margin-left:10px\">\n                                     <p class=\"lighting-description\" style=\"text-align:left;\"><font color=\"red\"> * </font> <i>Indicates items that are currently in stock in our domestic warehouse.</i> </p>\n                                  \n                        "}
{"title":"villa di como heritage 9053005-006-207","main category":"Dining Room","sub category":"","img":"https://www.amini.com/images/collections/9053000H/9053005-006-207.jpg","description":"\n                            <ul class=\"list-unstyled lighting-description\">\n                               <li> No: <span itemprop=\"brand\">9053005-006-207</span>  <font color=\"red\"> * </font> \n                               </li>\n                                  \n                                    <li><span class=\"title3\">Dimensions:</span> \n                                        <div id=\"dimensions\"> </div>\n                                    </li>  \n                                \n                               \n                                 <!--Start Top cavity-->\n                                                                  \n                                 <!--End Top cavity-->\n                                  \n                                    <li><span class=\"title3\">Finish:</span>\n                                      Heritage</li>\n                                  \n                            </ul>\n                                <p class=\"lighting-description\" style=\"text-align:left;\"><font color=\"red\"> * </font> <i>Indicates items that are currently in stock in our domestic warehouse.</i> </p>\n                                  \n                        "}
{"title":"melrose plaza 9019004R-118","main category":"Dining Room","sub category":"","img":"https://www.amini.com/images/collections/9019000/9019004R-118.jpg","description":"\n                            <ul class=\"list-unstyled lighting-description\">\n                               <li> No: <span itemprop=\"brand\">9019004R-118</span>  <font color=\"red\"> * </font> \n                               </li>\n                                  \n                                    <li><span class=\"title3\">Dimensions:</span> \n                                        <div id=\"dimensions\"> </div>\n                                    </li>  \n                                \n                               \n                                 <!--Start Top cavity-->\n                                                                  \n                                 <!--End Top cavity-->\n                                  \n                                    <li><span class=\"title3\">Finish:</span>\n                                      Dove</li>\n                                  \n                            </ul>\n                               \n                                        <img src=\"images/finish/Finish_118.jpg\" title=\"FINISH\" alt=\" \" style=\"margin-left:10px\">\n                                     <p class=\"lighting-description\" style=\"text-align:left;\"><font color=\"red\"> * </font> <i>Indicates items that are currently in stock in our domestic warehouse.</i> </p>\n                                  \n                        "}
{"title":"brooklyn walk KI-BRKW003-408","main category":"Dining Room","sub category":"","img":"https://www.amini.com/images/collections/BRKLYNWALK/KI-BRKW003-408.jpg","description":"\n                            <ul class=\"list-unstyled lighting-description\">\n                               <li> No: <span itemprop=\"brand\">KI-BRKW003-408</span>  <font color=\"red\"> * </font> \n                               </li>\n                                  \n                                    <li><span class=\"title3\">Dimensions:</span> \n                                        <div id=\"dimensions\"> </div>\n                                    </li>  \n                                \n                               \n                                 <!--Start Top cavity-->\n                                                                  \n                                 <!--End Top cavity-->\n                                  \n                                    <li><span class=\"title3\">Finish:</span>\n                                      Burnt Umber</li>\n                                  \n                            </ul>\n                                <p class=\"lighting-description\" style=\"text-align:left;\"><font color=\"red\"> * </font> <i>Indicates items that are currently in stock in our domestic warehouse.</i> </p>\n                                  \n                        "}
{"title":"paris chic 9003004A-409","main category":"Dining Room","sub category":"","img":"https://www.amini.com/images/collections/9003000/9003004A-409.jpg","description":"\n                            <ul class=\"list-unstyled lighting-description\">\n                               <li> No: <span itemprop=\"brand\">9003004A-409</span>  <font color=\"red\"> * </font> \n                               </li>\n                                  \n                                    <li><span class=\"title3\">Dimensions:</span> \n                                        <div id=\"dimensions\"> </div>\n                                    </li>  \n                                \n                               \n                                 <!--Start Top cavity-->\n                                                                  \n                                 <!--End Top cavity-->\n                                  \n                                    <li><span class=\"title3\">Finish:</span>\n                                      Espresso</li>\n                                  \n                            </ul>\n                                <p class=\"lighting-description\" style=\"text-align:left;\"><font color=\"red\"> * </font> <i>Indicates items that are currently in stock in our domestic warehouse.</i> </p>\n                                  \n                        "}
{"title":"villa valencia 72067-55","main category":"Dining Room","sub category":"","img":"https://www.amini.com/images/collections/72000/72067-55.jpg","description":"\n                            <ul class=\"list-unstyled lighting-description\">\n                               <li> No: <span itemprop=\"brand\">72067-55</span>  <font color=\"red\"> * </font> \n                               </li>\n                                  \n                                    <li><span class=\"title3\">Dimensions:</span> \n                                        <div id=\"dimensions\"> </div>\n                                    </li>  \n                                \n                               \n                                 <!--Start Top cavity-->\n                                                                  \n                                 <!--End Top cavity-->\n                                  \n                                    <li><span class=\"title3\">Finish:</span>\n                                      Classic Chestnut</li>\n                                  \n                            </ul>\n                               \n                                        <img src=\"images/finish/Finish_55.jpg\" title=\"FINISH\" alt=\" \" style=\"margin-left:10px\">\n                                     <p class=\"lighting-description\" style=\"text-align:left;\"><font color=\"red\"> * </font> <i>Indicates items that are currently in stock in our domestic warehouse.</i> </p>\n                                  \n                        "}
{"title":"lanterna 9032067-823","main category":"Dining Room","sub category":"","img":"https://www.amini.com/images/collections/9032000/9032067-823.jpg","description":"\n                            <ul class=\"list-unstyled lighting-description\">\n                               <li> No: <span itemprop=\"brand\">9032067-823</span>  <font color=\"red\"> * </font> \n                               </li>\n                                  \n                                    <li><span class=\"title3\">Dimensions:</span> \n                                        <div id=\"dimensions\"> </div>\n                                    </li>  \n                                \n                               \n                                 <!--Start Top cavity-->\n                                                                  \n                                 <!--End Top cavity-->\n                                  \n                                    <li><span class=\"title3\">Finish:</span>\n                                      Silver Mist</li>\n                                  \n                            </ul>\n                                <p class=\"lighting-description\" style=\"text-align:left;\"><font color=\"red\"> * </font> <i>Indicates items that are currently in stock in our domestic warehouse.</i> </p>\n                                  \n                        "}
{"title":"menlo station KI-MENP000-123","main category":"Dining Room","sub category":"","img":"https://www.amini.com/images/collections/MENLOSTION/KI-MENP000-123.jpg","description":"\n                            <ul class=\"list-unstyled lighting-description\">\n                               <li> No: <span itemprop=\"brand\">KI-MENP000-123</span>  <font color=\"red\"> * </font> \n                               </li>\n                                  \n                                    <li><span class=\"title3\">Dimensions:</span> \n                                        <div id=\"dimensions\"> </div>\n                                    </li>  \n                                \n                               \n                                 <!--Start Top cavity-->\n                                                                  \n                                 <!--End Top cavity-->\n                                  \n                                    <li><span class=\"title3\">Finish:</span>\n                                      Eucalyptus</li>\n                                  \n                            </ul>\n                                <p class=\"lighting-description\" style=\"text-align:left;\"><font color=\"red\"> * </font> <i>Indicates items that are currently in stock in our domestic warehouse.</i> </p>\n                                  \n                        "}
{"title":"glimmering heights 9011000-111","main category":"Dining Room","sub category":"","img":"https://www.amini.com/images/collections/9011000/9011000-111.jpg","description":"\n                            <ul class=\"list-unstyled lighting-description\">\n                               <li> No: <span itemprop=\"brand\">9011000-111</span>  <font color=\"red\"> * </font> \n                               </li>\n                                  \n                                    <li><span class=\"title3\">Dimensions:</span> \n                                        <div id=\"dimensions\"> </div>\n                                    </li>  \n                                \n                               \n                                 <!--Start Top cavity-->\n                                                                  \n                                 <!--End Top cavity-->\n                                  \n                                    <li><span class=\"title3\">Finish:</span>\n                                      Ivory</li>\n                                  \n                            </ul>\n                               \n                                        <img src=\"images/finish/Finish_111.jpg\" title=\"FINISH\" alt=\" \" style=\"margin-left:10px\">\n                                     <p class=\"lighting-description\" style=\"text-align:left;\"><font color=\"red\"> * </font> <i>Indicates items that are currently in stock in our domestic warehouse.</i> </p>\n                                  \n                        "}
{"title":"crossings KI-CRSG067-217","main category":"Dining Room","sub category":"","img":"https://www.amini.com/images/collections/CROSSINGS/KI-CRSG067-217.jpg","description":"\n                            <ul class=\"list-unstyled lighting-description\">\n                               <li> No: <span itemprop=\"brand\">KI-CRSG067-217</span>  <font color=\"red\"> * </font> \n                               </li>\n                                  \n                                    <li><span class=\"title3\">Dimensions:</span> \n                                        <div id=\"dimensions\"> </div>\n                                    </li>  \n                                \n                               \n                                 <!--Start Top cavity-->\n                                                                  \n                                 <!--End Top cavity-->\n                                  \n                                    <li><span class=\"title3\">Finish:</span>\n                                      Reclaimed Barn</li>\n                                  \n                            </ul>\n                                <p class=\"lighting-description\" style=\"text-align:left;\"><font color=\"red\"> * </font> <i>Indicates items that are currently in stock in our domestic warehouse.</i> </p>\n                                  \n                        "}
{"title":"menlo station KI-MENP067-123","main category":"Dining Room","sub category":"","img":"https://www.amini.com/images/collections/MENLOSTION/KI-MENP067-123.jpg","description":"\n                            <ul class=\"list-unstyled lighting-description\">\n                               <li> No: <span itemprop=\"brand\">KI-MENP067-123</span>  <font color=\"red\"> * </font> \n                               </li>\n                                  \n                                    <li><span class=\"title3\">Dimensions:</span> \n                                        <div id=\"dimensions\"> </div>\n                                    </li>  \n                                \n                               \n                                 <!--Start Top cavity-->\n                                                                  \n                                 <!--End Top cavity-->\n                                  \n                                    <li><span class=\"title3\">Finish:</span>\n                                      Eucalyptus</li>\n                                  \n                            </ul>\n                                <p class=\"lighting-description\" style=\"text-align:left;\"><font color=\"red\"> * </font> <i>Indicates items that are currently in stock in our domestic warehouse.</i> </p>\n                                  \n                        "}
{"title":"villa valencia 72007-67-55","main category":"Dining Room","sub category":"","img":"https://www.amini.com/images/collections/72000/72007-67-55.jpg","description":"\n                            <ul class=\"list-unstyled lighting-description\">\n                               <li> No: <span itemprop=\"brand\">72007-67-55</span>  <font color=\"red\"> * </font> \n                               </li>\n                                  \n                                    <li><span class=\"title3\">Dimensions:</span> \n                                        <div id=\"dimensions\"> </div>\n                                    </li>  \n                                \n                               \n                                 <!--Start Top cavity-->\n                                                                  \n                                 <!--End Top cavity-->\n                                  \n                                    <li><span class=\"title3\">Finish:</span>\n                                      Classic Chestnut</li>\n                                  \n                            </ul>\n                               \n                                        <img src=\"images/finish/Finish_55.jpg\" title=\"FINISH\" alt=\" \" style=\"margin-left:10px\">\n                                     <p class=\"lighting-description\" style=\"text-align:left;\"><font color=\"red\"> * </font> <i>Indicates items that are currently in stock in our domestic warehouse.</i> </p>\n                                  \n                        "}
{"title":"menlo station KI-MENP007-123","main category":"Dining Room","sub category":"","img":"https://www.amini.com/images/collections/MENLOSTION/KI-MENP007-123.jpg","description":"\n                            <ul class=\"list-unstyled lighting-description\">\n                               <li> No: <span itemprop=\"brand\">KI-MENP007-123</span>  <font color=\"red\"> * </font> \n                               </li>\n                                  \n                                    <li><span class=\"title3\">Dimensions:</span> \n                                        <div id=\"dimensions\"> </div>\n                                    </li>  \n                                \n                               \n                                 <!--Start Top cavity-->\n                                                                  \n                                 <!--End Top cavity-->\n                                  \n                                    <li><span class=\"title3\">Finish:</span>\n                                      Eucalyptus</li>\n                                  \n                            </ul>\n                                <p class=\"lighting-description\" style=\"text-align:left;\"><font color=\"red\"> * </font> <i>Indicates items that are currently in stock in our domestic warehouse.</i> </p>\n                                  \n                        "}
{"title":"glimmering heights 9011003R-111","main category":"Dining Room","sub category":"","img":"https://www.amini.com/images/collections/9011000/9011003R-111.jpg","description":"\n                            <ul class=\"list-unstyled lighting-description\">\n                               <li> No: <span itemprop=\"brand\">9011003R-111</span>  <font color=\"red\"> * </font> \n                               </li>\n                                  \n                                    <li><span class=\"title3\">Dimensions:</span> \n                                        <div id=\"dimensions\"> </div>\n                                    </li>  \n                                \n                               \n                                 <!--Start Top cavity-->\n                                                                  \n                                 <!--End Top cavity-->\n                                  \n                                    <li><span class=\"title3\">Finish:</span>\n                                      Ivory</li>\n                                  \n                            </ul>\n                               \n                                        <img src=\"images/finish/Finish_111.jpg\" title=\"FINISH\" alt=\" \" style=\"margin-left:10px\">\n                                     <p class=\"lighting-description\" style=\"text-align:left;\"><font color=\"red\"> * </font> <i>Indicates items that are currently in stock in our domestic warehouse.</i> </p>\n                                  \n                        "}
{"title":"villa valencia 72002-55","main category":"Dining Room","sub category":"","img":"https://www.amini.com/images/collections/72000/72002-55.jpg","description":"\n                            <ul class=\"list-unstyled lighting-description\">\n                               <li> No: <span itemprop=\"brand\">72002-55</span>  <font color=\"red\"> * </font> \n                               </li>\n                                  \n                                    <li><span class=\"title3\">Dimensions:</span> \n                                        <div id=\"dimensions\"> </div>\n                                    </li>  \n                                \n                               \n                                 <!--Start Top cavity-->\n                                                                  \n                                 <!--End Top cavity-->\n                                  \n                                    <li><span class=\"title3\">Finish:</span>\n                                      Classic Chestnut</li>\n                                  \n                            </ul>\n                               \n                                        <img src=\"images/finish/Finish_55.jpg\" title=\"FINISH\" alt=\" \" style=\"margin-left:10px\">\n                                     <p class=\"lighting-description\" style=\"text-align:left;\"><font color=\"red\"> * </font> <i>Indicates items that are currently in stock in our domestic warehouse.</i> </p>\n                                  \n                        "}
{"title":"laguna ridge 9083002-129","main category":"Dining Room","sub category":"","img":"https://www.amini.com/images/collections/9083000/9083002-129.jpg","description":"\n                            <ul class=\"list-unstyled lighting-description\">\n                               <li> No: <span itemprop=\"brand\">9083002-129</span>  <font color=\"red\"> * </font> \n                               </li>\n                                  \n                                    <li><span class=\"title3\">Dimensions:</span> \n                                        <div id=\"dimensions\"> </div>\n                                    </li>  \n                                \n                               \n                                 <!--Start Top cavity-->\n                                                                  \n                                 <!--End Top cavity-->\n                                  \n                                    <li><span class=\"title3\">Finish:</span>\n                                      Washed Oak</li>\n                                  \n                            </ul>\n                                <p class=\"lighting-description\" style=\"text-align:left;\"><font color=\"red\"> * </font> <i>Indicates items that are currently in stock in our domestic warehouse.</i> </p>\n                                  \n                        "}
{"title":"hudson ferry KI-HUDF067-216","main category":"Dining Room","sub category":"","img":"https://www.amini.com/images/collections/HUDSONFERY/KI-HUDF067-216.jpg","description":"\n                            <ul class=\"list-unstyled lighting-description\">\n                               <li> No: <span itemprop=\"brand\">KI-HUDF067-216</span>  <font color=\"red\"> * </font> \n                               </li>\n                                  \n                                    <li><span class=\"title3\">Dimensions:</span> \n                                        <div id=\"dimensions\"> </div>\n                                    </li>  \n                                \n                               \n                                 <!--Start Top cavity-->\n                                                                  \n                                 <!--End Top cavity-->\n                                  \n                                    <li><span class=\"title3\">Finish:</span>\n                                      Driftwood</li>\n                                  \n                            </ul>\n                                <p class=\"lighting-description\" style=\"text-align:left;\"><font color=\"red\"> * </font> <i>Indicates items that are currently in stock in our domestic warehouse.</i> </p>\n                                  \n                        "}
{"title":"melrose plaza 9019007-118","main category":"Dining Room","sub category":"","img":"https://www.amini.com/images/collections/9019000/9019007-118.jpg","description":"\n                            <ul class=\"list-unstyled lighting-description\">\n                               <li> No: <span itemprop=\"brand\">9019007-118</span>  <font color=\"red\"> * </font> \n                               </li>\n                                  \n                                    <li><span class=\"title3\">Dimensions:</span> \n                                        <div id=\"dimensions\"> </div>\n                                    </li>  \n                                \n                               \n                                 <!--Start Top cavity-->\n                                                                  \n                                 <!--End Top cavity-->\n                                  \n                                    <li><span class=\"title3\">Finish:</span>\n                                      Dove</li>\n                                  \n                            </ul>\n                               \n                                        <img src=\"images/finish/Finish_118.jpg\" title=\"FINISH\" alt=\" \" style=\"margin-left:10px\">\n                                     <p class=\"lighting-description\" style=\"text-align:left;\"><font color=\"red\"> * </font> <i>Indicates items that are currently in stock in our domestic warehouse.</i> </p>\n                                  \n                        "}
{"title":"brooklyn walk KI-BRKW900-408","main category":"Dining Room","sub category":"","img":"https://www.amini.com/images/collections/BRKLYNWALK/KI-BRKW900-408.jpg","description":"\n                            <ul class=\"list-unstyled lighting-description\">\n                               <li> No: <span itemprop=\"brand\">KI-BRKW900-408</span>  <font color=\"red\"> * </font> \n                               </li>\n                                  \n                                    <li><span class=\"title3\">Dimensions:</span> \n                                        <div id=\"dimensions\"> </div>\n                                    </li>  \n                                \n                               \n                                 <!--Start Top cavity-->\n                                                                  \n                                 <!--End Top cavity-->\n                                  \n                                    <li><span class=\"title3\">Finish:</span>\n                                      Burnt Umber</li>\n                                  \n                            </ul>\n                                <p class=\"lighting-description\" style=\"text-align:left;\"><font color=\"red\"> * </font> <i>Indicates items that are currently in stock in our domestic warehouse.</i> </p>\n                                  \n                        "}
{"title":"trance TR-RTRDM002","main category":"Dining Room","sub category":"","img":"https://www.amini.com/images/collections/TRANCE/TR-RTRDM002.jpg","description":"\n                            <ul class=\"list-unstyled lighting-description\">\n                               <li> No: <span itemprop=\"brand\">TR-RTRDM002</span>  <font color=\"red\"> * </font> \n                               </li>\n                                  \n                                    <li><span class=\"title3\">Dimensions:</span> \n                                        <div id=\"dimensions\"> </div>\n                                    </li>  \n                                \n                               \n                                 <!--Start Top cavity-->\n                                                                  \n                                 <!--End Top cavity-->\n                                  \n                            </ul>\n                                <p class=\"lighting-description\" style=\"text-align:left;\"><font color=\"red\"> * </font> <i>Indicates items that are currently in stock in our domestic warehouse.</i> </p>\n                                  \n                        "}
{"title":"lavelle 54003-04","main category":"Dining Room","sub category":"","img":"https://www.amini.com/images/collections/54000/54003-04.jpg","description":"\n                            <ul class=\"list-unstyled lighting-description\">\n                               <li> No: <span itemprop=\"brand\">54003-04</span>  <font color=\"red\"> * </font> \n                               </li>\n                                  \n                                    <li><span class=\"title3\">Dimensions:</span> \n                                        <div id=\"dimensions\"> </div>\n                                    </li>  \n                                \n                               \n                                 <!--Start Top cavity-->\n                                                                  \n                                 <!--End Top cavity-->\n                                  \n                                    <li><span class=\"title3\">Finish:</span>\n                                      Blanc</li>\n                                  \n                            </ul>\n                               \n                                        <img src=\"images/finish/Finish_04.jpg\" title=\"FINISH\" alt=\" \" style=\"margin-left:10px\">\n                                     <p class=\"lighting-description\" style=\"text-align:left;\"><font color=\"red\"> * </font> <i>Indicates items that are currently in stock in our domestic warehouse.</i> </p>\n                                  \n                        "}
{"title":"sky tower 9025667-108","main category":"Dining Room","sub category":"","img":"https://www.amini.com/images/collections/9025000/9025667-108.jpg","description":"\n                            <ul class=\"list-unstyled lighting-description\">\n                               <li> No: <span itemprop=\"brand\">9025667-108</span>  <font color=\"red\"> * </font> \n                               </li>\n                                  \n                                    <li><span class=\"title3\">Dimensions:</span> \n                                        <div id=\"dimensions\"> </div>\n                                    </li>  \n                                \n                               \n                                 <!--Start Top cavity-->\n                                                                  \n                                 <!--End Top cavity-->\n                                  \n                                    <li><span class=\"title3\">Finish:</span>\n                                      White Cloud</li>\n                                  \n                            </ul>\n                                <p class=\"lighting-description\" style=\"text-align:left;\"><font color=\"red\"> * </font> <i>Indicates items that are currently in stock in our domestic warehouse.</i> </p>\n                                  \n                        "}
{"title":"21 cosmopolitan orange 9029002-812","main category":"Dining Room","sub category":"","img":"https://www.amini.com/images/collections/9029000/9029002-812.jpg","description":"\n                            <ul class=\"list-unstyled lighting-description\">\n                               <li> No: <span itemprop=\"brand\">9029002-812</span>  <font color=\"red\"> * </font> \n                               </li>\n                                 \n                               \n                                 <!--Start Top cavity-->\n                                                                  \n                                 <!--End Top cavity-->\n                                  \n                                    <li><span class=\"title3\">Finish:</span>\n                                      Diablo Orange/Umber</li>\n                                  \n                            </ul>\n                                <p class=\"lighting-description\" style=\"text-align:left;\"><font color=\"red\"> * </font> <i>Indicates items that are currently in stock in our domestic warehouse.</i> </p>\n                                  \n                        "}
{"title":"laguna ridge 9083003-814","main category":"Dining Room","sub category":"","img":"https://www.amini.com/images/collections/9083000/9083003-814.jpg","description":"\n                            <ul class=\"list-unstyled lighting-description\">\n                               <li> No: <span itemprop=\"brand\">9083003-814</span>  <font color=\"red\"> * </font> \n                               </li>\n                                  \n                                    <li><span class=\"title3\">Dimensions:</span> \n                                        <div id=\"dimensions\"> </div>\n                                    </li>  \n                                \n                               \n                                 <!--Start Top cavity-->\n                                                                  \n                                 <!--End Top cavity-->\n                                  \n                                    <li><span class=\"title3\">Finish:</span>\n                                      Brushed Silver</li>\n                                  \n                            </ul>\n                                <p class=\"lighting-description\" style=\"text-align:left;\"><font color=\"red\"> * </font> <i>Indicates items that are currently in stock in our domestic warehouse.</i> </p>\n                                  \n                        "}
{"title":"glimmering heights 9011007-111","main category":"Dining Room","sub category":"","img":"https://www.amini.com/images/collections/9011000/9011007-111.jpg","description":"\n                            <ul class=\"list-unstyled lighting-description\">\n                               <li> No: <span itemprop=\"brand\">9011007-111</span>  <font color=\"red\"> * </font> \n                               </li>\n                                  \n                                    <li><span class=\"title3\">Dimensions:</span> \n                                        <div id=\"dimensions\"> </div>\n                                    </li>  \n                                \n                               \n                                 <!--Start Top cavity-->\n                                                                  \n                                 <!--End Top cavity-->\n                                  \n                                    <li><span class=\"title3\">Finish:</span>\n                                      Ivory</li>\n                                  \n                            </ul>\n                               \n                                        <img src=\"images/finish/Finish_111.jpg\" title=\"FINISH\" alt=\" \" style=\"margin-left:10px\">\n                                     <p class=\"lighting-description\" style=\"text-align:left;\"><font color=\"red\"> * </font> <i>Indicates items that are currently in stock in our domestic warehouse.</i> </p>\n                                  \n                        "}
{"title":"windsor court 70067-54","main category":"Dining Room","sub category":"","img":"https://www.amini.com/images/collections/70000/70067-54.jpg","description":"\n                            <ul class=\"list-unstyled lighting-description\">\n                               <li> No: <span itemprop=\"brand\">70067-54</span>  <font color=\"red\"> * </font> \n                               </li>\n                                  \n                                    <li><span class=\"title3\">Dimensions:</span> \n                                        <div id=\"dimensions\"> </div>\n                                    </li>  \n                                \n                               \n                                 <!--Start Top cavity-->\n                                                                  \n                                 <!--End Top cavity-->\n                                  \n                                    <li><span class=\"title3\">Finish:</span>\n                                      Vintage Fruitwood</li>\n                                  \n                            </ul>\n                               \n                                        <img src=\"images/finish/Finish_54.jpg\" title=\"FINISH\" alt=\" \" style=\"margin-left:10px\">\n                                     <p class=\"lighting-description\" style=\"text-align:left;\"><font color=\"red\"> * </font> <i>Indicates items that are currently in stock in our domestic warehouse.</i> </p>\n                                  \n                        "}
{"title":"silverlake village KI-SLVG067-129","main category":"Dining Room","sub category":"","img":"https://www.amini.com/images/collections/SLVRLKVLAG/KI-SLVG067-129.jpg","description":"\n                            <ul class=\"list-unstyled lighting-description\">\n                               <li> No: <span itemprop=\"brand\">KI-SLVG067-129</span>  <font color=\"red\"> * </font> \n                               </li>\n                                  \n                                    <li><span class=\"title3\">Dimensions:</span> \n                                        <div id=\"dimensions\"> </div>\n                                    </li>  \n                                \n                               \n                                 <!--Start Top cavity-->\n                                                                  \n                                 <!--End Top cavity-->\n                                  \n                                    <li><span class=\"title3\">Finish:</span>\n                                      Washed Oak</li>\n                                  \n                            </ul>\n                                <p class=\"lighting-description\" style=\"text-align:left;\"><font color=\"red\"> * </font> <i>Indicates items that are currently in stock in our domestic warehouse.</i> </p>\n                                  \n                        "}
{"title":"paris chic 9003209-409","main category":"Dining Room","sub category":"","img":"https://www.amini.com/images/collections/9003000/9003209-409.jpg","description":"\n                            <ul class=\"list-unstyled lighting-description\">\n                               <li> No: <span itemprop=\"brand\">9003209-409</span>  <font color=\"red\"> * </font> \n                               </li>\n                                  \n                                    <li><span class=\"title3\">Dimensions:</span> \n                                        <div id=\"dimensions\"> </div>\n                                    </li>  \n                                \n                               \n                                 <!--Start Top cavity-->\n                                                                  \n                                 <!--End Top cavity-->\n                                  \n                                    <li><span class=\"title3\">Finish:</span>\n                                      Espresso</li>\n                                  \n                            </ul>\n                                <p class=\"lighting-description\" style=\"text-align:left;\"><font color=\"red\"> * </font> <i>Indicates items that are currently in stock in our domestic warehouse.</i> </p>\n                                  \n                        "}
{"title":"laguna ridge 9083007-129","main category":"Dining Room","sub category":"","img":"https://www.amini.com/images/collections/9083000/9083007-129.jpg","description":"\n                            <ul class=\"list-unstyled lighting-description\">\n                               <li> No: <span itemprop=\"brand\">9083007-129</span>  <font color=\"red\"> * </font> \n                               </li>\n                                  \n                                    <li><span class=\"title3\">Dimensions:</span> \n                                        <div id=\"dimensions\"> </div>\n                                    </li>  \n                                \n                               \n                                 <!--Start Top cavity-->\n                                                                  \n                                 <!--End Top cavity-->\n                                  \n                                    <li><span class=\"title3\">Finish:</span>\n                                      Washed Oak</li>\n                                  \n                            </ul>\n                                <p class=\"lighting-description\" style=\"text-align:left;\"><font color=\"red\"> * </font> <i>Indicates items that are currently in stock in our domestic warehouse.</i> </p>\n                                  \n                        "}
{"title":"camden court 9005001-101-126","main category":"Dining Room","sub category":"","img":"https://www.amini.com/images/collections/9005000/9005001-101-126.jpg","description":"\n                            <ul class=\"list-unstyled lighting-description\">\n                               <li> No: <span itemprop=\"brand\">9005001-101-126</span>  <font color=\"red\"> * </font> \n                               </li>\n                                  \n                                    <li><span class=\"title3\">Dimensions:</span> \n                                        <div id=\"dimensions\"> </div>\n                                    </li>  \n                                \n                               \n                                 <!--Start Top cavity-->\n                                                                  \n                                 <!--End Top cavity-->\n                                  \n                                    <li><span class=\"title3\">Finish:</span>\n                                      Pearl</li>\n                                  \n                            </ul>\n                                <p class=\"lighting-description\" style=\"text-align:left;\"><font color=\"red\"> * </font> <i>Indicates items that are currently in stock in our domestic warehouse.</i> </p>\n                                  \n                        "}
{"title":"eclipse KI-ECLP007-135","main category":"Dining Room","sub category":"","img":"https://www.amini.com/images/collections/ECLIPSE/KI-ECLP007-135.jpg","description":"\n                            <ul class=\"list-unstyled lighting-description\">\n                               <li> No: <span itemprop=\"brand\">KI-ECLP007-135</span>  <font color=\"red\"> * </font> \n                               </li>\n                                  \n                                    <li><span class=\"title3\">Dimensions:</span> \n                                        <div id=\"dimensions\"> </div>\n                                    </li>  \n                                \n                               \n                                 <!--Start Top cavity-->\n                                                                  \n                                 <!--End Top cavity-->\n                                  \n                                    <li><span class=\"title3\">Finish:</span>\n                                      Moonlight</li>\n                                  \n                            </ul>\n                                <p class=\"lighting-description\" style=\"text-align:left;\"><font color=\"red\"> * </font> <i>Indicates items that are currently in stock in our domestic warehouse.</i> </p>\n                                  \n                        "}
{"title":"del mar sound KI-DELM260-215","main category":"Dining Room","sub category":"","img":"https://www.amini.com/images/collections/DLMARSOUND/KI-DELM260-215.jpg","description":"\n                            <ul class=\"list-unstyled lighting-description\">\n                               <li> No: <span itemprop=\"brand\">KI-DELM260-215</span>  <font color=\"red\"> * </font> \n                               </li>\n                                  \n                                    <li><span class=\"title3\">Dimensions:</span> \n                                        <div id=\"dimensions\"> </div>\n                                    </li>  \n                                \n                               \n                                 <!--Start Top cavity-->\n                                                                  \n                                 <!--End Top cavity-->\n                                  \n                                    <li><span class=\"title3\">Finish:</span>\n                                      Boardwalk</li>\n                                  \n                            </ul>\n                                <p class=\"lighting-description\" style=\"text-align:left;\"><font color=\"red\"> * </font> <i>Indicates items that are currently in stock in our domestic warehouse.</i> </p>\n                                  \n                        "}
{"title":"roxbury park - v129 9006007-220","main category":"Dining Room","sub category":"","img":"https://www.amini.com/images/collections/9006000/9006007-220.jpg","description":"\n                            <ul class=\"list-unstyled lighting-description\">\n                               <li> No: <span itemprop=\"brand\">9006007-220</span>  <font color=\"red\"> * </font> \n                               </li>\n                                  \n                                    <li><span class=\"title3\">Dimensions:</span> \n                                        <div id=\"dimensions\"> </div>\n                                    </li>  \n                                \n                               \n                                 <!--Start Top cavity-->\n                                                                  \n                                 <!--End Top cavity-->\n                                  \n                                    <li><span class=\"title3\">Finish:</span>\n                                      Slate</li>\n                                  \n                            </ul>\n                                <p class=\"lighting-description\" style=\"text-align:left;\"><font color=\"red\"> * </font> <i>Indicates items that are currently in stock in our domestic warehouse.</i> </p>\n                                  \n                        "}
{"title":"windsor court 70007-67-54","main category":"Dining Room","sub category":"","img":"https://www.amini.com/images/collections/70000/70007-67-54.jpg","description":"\n                            <ul class=\"list-unstyled lighting-description\">\n                               <li> No: <span itemprop=\"brand\">70007-67-54</span>  <font color=\"red\"> * </font> \n                               </li>\n                                  \n                                    <li><span class=\"title3\">Dimensions:</span> \n                                        <div id=\"dimensions\"> </div>\n                                    </li>  \n                                \n                               \n                                 <!--Start Top cavity-->\n                                                                  \n                                 <!--End Top cavity-->\n                                  \n                                    <li><span class=\"title3\">Finish:</span>\n                                      Vintage Fruitwood</li>\n                                  \n                            </ul>\n                               \n                                        <img src=\"images/finish/Finish_54.jpg\" title=\"FINISH\" alt=\" \" style=\"margin-left:10px\">\n                                     <p class=\"lighting-description\" style=\"text-align:left;\"><font color=\"red\"> * </font> <i>Indicates items that are currently in stock in our domestic warehouse.</i> </p>\n                                  \n                        "}
{"title":"villa valencia 72007-55","main category":"Dining Room","sub category":"","img":"https://www.amini.com/images/collections/72000/72007-55.jpg","description":"\n                            <ul class=\"list-unstyled lighting-description\">\n                               <li> No: <span itemprop=\"brand\">72007-55</span>  <font color=\"red\"> * </font> \n                               </li>\n                                  \n                                    <li><span class=\"title3\">Dimensions:</span> \n                                        <div id=\"dimensions\"> </div>\n                                    </li>  \n                                \n                               \n                                 <!--Start Top cavity-->\n                                                                  \n                                 <!--End Top cavity-->\n                                  \n                                    <li><span class=\"title3\">Finish:</span>\n                                      Classic Chestnut</li>\n                                  \n                            </ul>\n                               \n                                        <img src=\"images/finish/Finish_55.jpg\" title=\"FINISH\" alt=\" \" style=\"margin-left:10px\">\n                                     <p class=\"lighting-description\" style=\"text-align:left;\"><font color=\"red\"> * </font> <i>Indicates items that are currently in stock in our domestic warehouse.</i> </p>\n                                  \n                        "}
